spatialkfold/__init__.py
spatialkfold/blocks.py
spatialkfold/clusters.py
spatialkfold/datasets.py
spatialkfold/plotting.py
spatialkfold/stats.py
spatialkfold/data/ames.geojson
spatial_kfold-0.0.4.dist-info/LICENSE
spatial_kfold-0.0.4.dist-info/METADATA
spatial_kfold-0.0.4.dist-info/WHEEL
spatial_kfold-0.0.4.dist-info/top_level.txt
spatial_kfold-0.0.4.dist-info/RECORD
