Metadata-Version: 2.1
Name: spatial-kfold
Version: 0.0.4
Summary: spatial-kfold: A Python Package for Spatial Resampling Toward More Reliable Cross-Validation in Spatial Studies.
Home-page: https://github.com/WalidGharianiEAGLE/spatial-kfold
Author: Walid Ghariani
Author-email: walid11ghariani@gmail.com
License: GPL-3.0
Keywords: cross-validation,machine-learning,GIS,spatial
Classifier: Development Status :: 3 - Alpha
Classifier: Intended Audience :: Science/Research
Classifier: License :: OSI Approved :: MIT License
Classifier: Programming Language :: Python :: 3
Classifier: Programming Language :: Python :: 3.7
Classifier: Programming Language :: Python :: 3.8
Classifier: Programming Language :: Python :: 3.9
Classifier: Programming Language :: Python :: 3.10
Classifier: Programming Language :: Python :: 3.11
Classifier: Programming Language :: Python :: 3.12
Classifier: Programming Language :: Python :: 3.13
Requires-Python: >=3.7
License-File: LICENSE
Requires-Dist: pandas >=0.20
Requires-Dist: numpy >=1.10.0
Requires-Dist: geopandas >=0.3
Requires-Dist: shapely >=1.6
Requires-Dist: matplotlib >=2.2.4
Requires-Dist: scikit-learn >=0.22
